Metadata-Version: 2.4
Name: checkm-genome
Version: 1.2.4
Summary: Assess the quality of putative genome bins.
Home-page: http://pypi.python.org/pypi/checkm-genome/
Author: Donovan Parks, Michael Imelfort, Connor Skennerton
Author-email: donovan.parks@gmail.com
License: GPL3
Classifier: Development Status :: 5 - Production/Stable
Classifier: Intended Audience :: Science/Research
Classifier: License :: OSI Approved :: GNU General Public License v3 (GPLv3)
Classifier: Natural Language :: English
Classifier: Programming Language :: Python :: 3.6
Classifier: Topic :: Scientific/Engineering :: Bio-Informatics
License-File: LICENSE
Requires-Dist: numpy>=1.21.3
Requires-Dist: scipy>=1.7.3
Requires-Dist: matplotlib>=3.5.1
Requires-Dist: pysam>=0.19.0
Requires-Dist: dendropy>=4.5.2
Requires-Dist: setuptools
Dynamic: author
Dynamic: author-email
Dynamic: classifier
Dynamic: description
Dynamic: description-content-type
Dynamic: home-page
Dynamic: license
Dynamic: license-file
Dynamic: requires-dist
Dynamic: summary
